<annotation>
	<folder>damaged</folder>
	<filename>2btmpeg.jpg</filename>
	<path>D:\DataScience\iNeuron\DeepLearning\WindmillFaultDetection\image\damaged\2btmpeg.jpg</path>
	<source>
		<database>Unknown</database>
	</source>
	<size>
		<width>450</width>
		<height>320</height>
		<depth>3</depth>
	</size>
	<segmented>0</segmented>
	<object>
		<name>faulty</name>
		<pose>Unspecified</pose>
		<truncated>0</truncated>
		<difficult>0</difficult>
		<bndbox>
			<xmin>149</xmin>
			<ymin>119</ymin>
			<xmax>343</xmax>
			<ymax>201</ymax>
		</bndbox>
	</object>
</annotation>
